setup.py
lazyTest/__init__.py
lazyTest/case.py
lazyTest/page.py
lazyTest/utils.py
lazyTest.egg-info/PKG-INFO
lazyTest.egg-info/SOURCES.txt
lazyTest.egg-info/dependency_links.txt
lazyTest.egg-info/entry_points.txt
lazyTest.egg-info/requires.txt
lazyTest.egg-info/top_level.txt
lazyTest/base/__init__.py
lazyTest/base/base.py
lazyTest/base/config.py
lazyTest/base/file.py
lazyTest/base/lazy_log.py
lazyTest/base/utils.py
lazyTest/cli/__init__.py
lazyTest/cli/cli.py
lazyTest/cli/template.py
lazyTest/model/__init__.py
lazyTest/model/elemetSource.py