Metadata-Version: 1.0
Name: lazyTest
Version: 2.0.9
Summary: 自动化测试框架
Home-page: https://github.com/xingheyang/lazyTest.git
Author: buxiubuzhi
Author-email: xingheyang_99@163.com
License: UNKNOWN
Keywords: pip,lazyTest
Platform: UNKNOWN
